openml_cli/__init__.py
openml_cli/__version__.txt
openml_cli/swagger.yml
openml_cli/api/API.py
openml_cli/api/Config.py
openml_cli/api/__init__.py
openml_cli/cli/__init__.py
openml_cli/cli/__main__.py
openml_cli/cli/main_config.py
openml_cli/cli/main_dataset.py
openml_cli/utils/__init__.py
openml_cli-0.1.0.dist-info/LICENSE.txt
openml_cli-0.1.0.dist-info/METADATA
openml_cli-0.1.0.dist-info/RECORD
openml_cli-0.1.0.dist-info/WHEEL
openml_cli-0.1.0.dist-info/entry_points.txt
openml_cli-0.1.0.dist-info/top_level.txt
